terbilang
