Metadata-Version: 2.1
Name: terbilang
Version: 0.0.6
Summary: Python Terbilang
Home-page: https://github.com/nggit/terbilang
Author: nggit
Author-email: contact@anggit.com
License: MIT
Platform: UNKNOWN
Classifier: Development Status :: 5 - Production/Stable
Classifier: License :: OSI Approved :: MIT License
Classifier: Operating System :: OS Independent
